runp/__init__.py
runp/runp.py
tests/__init__.py
tests/test.py
tests/testfile.py
runp3-0.0.6.dist-info/METADATA
runp3-0.0.6.dist-info/WHEEL
runp3-0.0.6.dist-info/entry_points.txt
runp3-0.0.6.dist-info/top_level.txt
runp3-0.0.6.dist-info/RECORD
