Metadata-Version: 2.1
Name: runp3
Version: 0.0.6
Summary: runp exports Python functions from files to the command line
Home-page: https://github.com/TakashiKusachi/runp
Author: Takashi Kusachi
Author-email: aisiars@gmail.com
License: UNKNOWN
Platform: UNKNOWN
Classifier: Environment :: Console
Classifier: Intended Audience :: Developers
Classifier: Programming Language :: Python :: 3.7
Classifier: Programming Language :: Python :: 3.8
Classifier: Programming Language :: Python :: 3.9
Classifier: Programming Language :: Python :: 3.10
Classifier: Topic :: Software Development
Requires-Python: >3.7.11
